meticulous/__init__.py
meticulous/api.py
meticulous/api_types.py
meticulous/profile.py
pymeticulous-0.3.1.dist-info/licenses/LICENSE
pymeticulous-0.3.1.dist-info/METADATA
pymeticulous-0.3.1.dist-info/WHEEL
pymeticulous-0.3.1.dist-info/top_level.txt
pymeticulous-0.3.1.dist-info/RECORD
