Metadata-Version: 2.4
Name: pyMeticulous
Version: 0.3.1
Summary: Integration with the meticulouscoffee machine via its REST API
Author-email: Meticulous <support@meticuloushome.com>
Requires-Python: >=3.11
License-File: LICENSE
Requires-Dist: requests>=2.32.3
Requires-Dist: pydantic>=2.7.3
Requires-Dist: python-socketio>=5.11.2
Requires-Dist: websocket-client>=1.8.0
Requires-Dist: zstandard>=0.22.0
Provides-Extra: test
Requires-Dist: pytest>=8.2.2; extra == "test"
Requires-Dist: flake8>=7.0.0; extra == "test"
Requires-Dist: flake8-deprecated>=1.3.0; extra == "test"
Dynamic: license-file
